django_htmx_tools/__init__.py
django_htmx_tools/middleware/__init__.py
django_htmx_tools/middleware/htmx.py
django_htmx_tools/utils/__init__.py
django_htmx_tools/utils/htmx.py
django_htmx_tools/views/__init__.py
django_htmx_tools/views/decorators.py
django_htmx_tools/views/mixins.py
django_htmx_tools-1.0.2.dist-info/METADATA
django_htmx_tools-1.0.2.dist-info/WHEEL
django_htmx_tools-1.0.2.dist-info/licenses/LICENSE
django_htmx_tools-1.0.2.dist-info/RECORD
