Metadata-Version: 2.4
Name: django-htmx-tools
Version: 1.0.2
Summary: An assortment of Django mixins and middleware for working with HTMX
Project-URL: Homepage, https://github.com/howieweiner/django-htmx-tools
Project-URL: Repository, https://github.com/howieweiner/django-htmx-tools.git
Project-URL: Issues, https://github.com/howieweiner/django-htmx-tools/issues
Project-URL: Documentation, https://django-htmx-tools.readthedocs.io/
Author-email: Howie Weiner <hello@builtbyhowie.co.uk>
License-Expression: MIT
License-File: LICENSE
Keywords: django,htmx
Classifier: Development Status :: 3 - Alpha
Classifier: Framework :: Django
Classifier: Framework :: Django :: 4.2
Classifier: Framework :: Django :: 5.0
Classifier: Framework :: Django :: 5.1
Classifier: Framework :: Django :: 5.2
Classifier: Framework :: Django :: 6.0
Classifier: Intended Audience :: Developers
Classifier: License :: OSI Approved :: MIT License
Classifier: Natural Language :: English
Classifier: Operating System :: OS Independent
Classifier: Programming Language :: Python
Classifier: Programming Language :: Python :: 3
Classifier: Programming Language :: Python :: 3.10
Classifier: Programming Language :: Python :: 3.11
Classifier: Programming Language :: Python :: 3.12
Classifier: Programming Language :: Python :: 3.13
Classifier: Programming Language :: Python :: 3.14
Requires-Python: >=3.10
Requires-Dist: django>=4.2
Provides-Extra: dev
Requires-Dist: commitizen>=3.0; extra == 'dev'
Requires-Dist: django-stubs>=4.2; extra == 'dev'
Requires-Dist: mypy>=1.0; extra == 'dev'
Requires-Dist: pre-commit>=3.0; extra == 'dev'
Requires-Dist: pytest-cov>=4.0; extra == 'dev'
Requires-Dist: pytest-django>=4.5; extra == 'dev'
Requires-Dist: pytest>=7.0; extra == 'dev'
Requires-Dist: ruff>=0.1.0; extra == 'dev'
Provides-Extra: docs
Requires-Dist: sphinx-autodoc-typehints>=1.24; extra == 'docs'
Requires-Dist: sphinx-rtd-theme>=2.0; extra == 'docs'
Requires-Dist: sphinx>=7.0; extra == 'docs'
Provides-Extra: test
Requires-Dist: pytest-cov>=4.0; extra == 'test'
Requires-Dist: pytest-django>=4.5; extra == 'test'
Requires-Dist: pytest>=7.0; extra == 'test'
